[
  {
    "name": "Josh",
    "key": "Josh",
    "claimed": true
  },
  {
    "name": "Cortez",
    "key": "Cortez",
    "devices": [
      {
        "token": "legacy",
        "ua": ""
      },
      {
        "token": "d291342d-1bb2-4752-b0da-8ea6f45be96c",
        "ua": "Mozilla/5.0 (X11; CrOS x86_64 14541.0.0) AppleWebKit/537.36 (KHTML, like Gecko) Chrome/138.0.0.0 Safari/537.36"
      }
    ]
  },
  {
    "name": "Aadil",
    "key": "Aadil",
    "claimed": true
  },
  {
    "name": "Aaron",
    "key": "Aaron",
    "devices": [
      {
        "token": "legacy",
        "ua": ""
      },
      {
        "token": "39f62d1b-b83e-4cb6-bdd1-c4983a3a7139",
        "ua": "Mozilla/5.0 (X11; CrOS x86_64 14541.0.0) AppleWebKit/537.36 (KHTML, like Gecko) Chrome/138.0.0.0 Safari/537.36"
      }
    ]
  },
  {
    "name": "Brad",
    "key": "Brad",
    "claimed": true
  },
  {
    "name": "Sauveur",
    "key": "Sauveur",
    "devices": [
      {
        "token": "legacy",
        "ua": ""
      },
      {
        "token": "3235934f-fa24-4efa-9baa-32ad5db2d934",
        "ua": "Mozilla/5.0 (X11; CrOS x86_64 14541.0.0) AppleWebKit/537.36 (KHTML, like Gecko) Chrome/138.0.0.0 Safari/537.36"
      }
    ]
  },
  {
    "name": "Samuel",
    "key": "Samuel",
    "devices": [
      {
        "token": "legacy",
        "ua": ""
      },
      {
        "token": "d5f3e6a0-ea08-41ab-abd7-29b2fe30ec97",
        "ua": "Mozilla/5.0 (X11; CrOS x86_64 14541.0.0) AppleWebKit/537.36 (KHTML, like Gecko) Chrome/138.0.0.0 Safari/537.36"
      }
    ]
  },
  {
    "name": "Kaua",
    "key": "Kaua",
    "claimed": true
  },
  {
    "name": "Marcko",
    "key": "Marcko",
    "claimed": false
  },
  {
    "name": "Bryan",
    "key": "Bryan",
    "claimed": true
  },
  {
    "name": "Eli",
    "key": "Eli",
    "devices": [
      {
        "token": "legacy",
        "ua": ""
      },
      {
        "token": "41675197-7b26-491e-a5b6-1583e13492f6",
        "ua": "Mozilla/5.0 (X11; CrOS x86_64 14541.0.0) AppleWebKit/537.36 (KHTML, like Gecko) Chrome/138.0.0.0 Safari/537.36"
      }
    ]
  },
  {
    "name": "Riley",
    "key": "Riley",
    "claimed": true
  },
  {
    "name": "Hector",
    "key": "Hector",
    "claimed": true
  },
  {
    "name": "Raul",
    "key": "Raul",
    "claimed": true
  },
  {
    "name": "Alexander",
    "key": "Alexander",
    "claimed": false
  },
  {
    "name": "Jadiel",
    "key": "Jadiel",
    "claimed": true
  },
  {
    "name": "Bernice",
    "key": "Bernice",
    "claimed": false
  },
  {
    "name": "Sophie",
    "key": "Sophie",
    "claimed": true
  },
  {
    "name": "Matthew",
    "key": "Matthew",
    "claimed": true
  },
  {
    "name": "Jason",
    "key": "Jason",
    "claimed": true
  },
  {
    "name": "Alexis",
    "key": "Alexis",
    "claimed": true
  },
  {
    "name": "Nelson",
    "key": "Nelson",
    "claimed": true
  },
  {
    "name": "Hudson",
    "key": "Hudson",
    "claimed": false
  },
  {
    "name": "Kye Cenat",
    "key": "Kye Cenat",
    "claimed": true
  },
  {
    "name": "Kaden",
    "key": "Kaden",
    "claimed": false
  },
  {
    "name": "Jose",
    "key": "Jose",
    "devices": [
      {
        "token": "legacy",
        "ua": ""
      },
      {
        "token": "8317bbf7-ad08-49e6-b7e3-7166f714db12",
        "ua": "Mozilla/5.0 (X11; CrOS x86_64 14541.0.0) AppleWebKit/537.36 (KHTML, like Gecko) Chrome/138.0.0.0 Safari/537.36"
      }
    ]
  },
  {
    "name": "Bryan C",
    "key": "Bryan C",
    "claimed": true
  },
  {
    "name": "AJ",
    "key": "AJ",
    "devices": [
      {
        "token": "legacy",
        "ua": ""
      },
      {
        "token": "0e24b117-2b6b-4c28-9a79-82b302d99b25",
        "ua": "Mozilla/5.0 (X11; CrOS x86_64 14541.0.0) AppleWebKit/537.36 (KHTML, like Gecko) Chrome/138.0.0.0 Safari/537.36"
      }
    ]
  },
  {
    "name": "Testing",
    "key": "Testing",
    "devices": [
      {
        "token": "2d9ae0ab-45fe-4b5f-ac9e-89fbe97c8efd",
        "ua": "Mozilla/5.0 (Windows NT 10.0; Win64; x64) AppleWebKit/537.36 (KHTML, like Gecko) Chrome/148.0.0.0 Safari/537.36"
      }
    ]
  },
  {
    "name": "Santiago",
    "key": "Santiago",
    "devices": [
      {
        "token": "legacy",
        "ua": ""
      },
      {
        "token": "49fa6ea3-f1bd-462d-909e-1f2a6c59c184",
        "ua": "Mozilla/5.0 (X11; CrOS x86_64 14541.0.0) AppleWebKit/537.36 (KHTML, like Gecko) Chrome/138.0.0.0 Safari/537.36"
      }
    ]
  },
  {
    "name": "Aiden",
    "key": "Aiden",
    "claimed": true
  },
  {
    "name": "Dvinci",
    "key": "Dvinci",
    "claimed": true
  },
  {
    "name": "Nema",
    "key": "Nema"
    "claimed": false
     "devices":
  }
    {
      "name": "Test1"
      "key": "Test1"
      "claimed": false
       "devices":
    }
  }
]